{
  "error_variants": [
    {"name":"MissingPrompt","status":"retained","rationale":"The lowered-only public runtime still needs a missing-delimiter failure."},
    {"name":"CrossThread","status":"retained","rationale":"Runtime ownership remains thread-affine even after the stackful backend is gone."},
    {"name":"RuntimeBusy","status":"retained","rationale":"Active-runtime teardown misuse remains a public runtime concern."},
    {"name":"RuntimeDestroyed","status":"retained","rationale":"Destroyed-runtime misuse remains a public runtime concern."},
    {"name":"NonDiagonalComplete","status":"retained","rationale":"Non-diagonal completion is still part of the public shift/reset semantic contract."},
    {"name":"AlreadyResolved","status":"retained","rationale":"The current public root still aliases the raw stack-runtime error set, so this variant remains exported for now."},
    {"name":"NestedNonDiagonalCapture","status":"retained","rationale":"The current public root still aliases the raw stack-runtime error set, so this stackful capture detail remains exported for now."}
  ]
}
